setup.py
BINEM/__init__.py
BINEM/add.py
BINEM/sum.py
BINEM.egg-info/PKG-INFO
BINEM.egg-info/SOURCES.txt
BINEM.egg-info/dependency_links.txt
BINEM.egg-info/top_level.txt
BINEM.egg-info/zip-safe